vectorai/__init__.py
vectorai/client.py
vectorai/doc_utils.py
vectorai/errors.py
vectorai/options.py
vectorai/read.py
vectorai/utils.py
vectorai/write.py
vectorai/analytics/__init__.py
vectorai/analytics/analytics.py
vectorai/analytics/client.py
vectorai/analytics/comparator.py
vectorai/analytics/dimensionality_reduction.py
vectorai/analytics/relational_documents.py
vectorai/analytics/score.py
vectorai/analytics/tables.py
vectorai/analytics/utils.py
vectorai/analytics/viz.py
vectorai/analytics/api/__init__.py
vectorai/analytics/api/comparator.py
vectorai/analytics/scorer/__init__.py
vectorai/analytics/scorer/base_scorer.py
vectorai/analytics/scorer/cosine_scorer.py
vectorai/api/__init__.py
vectorai/api/api.py
vectorai/api/array_dict_vectorizer.py
vectorai/api/audio.py
vectorai/api/client.py
vectorai/api/cluster.py
vectorai/api/dimensionality_reduction.py
vectorai/api/image.py
vectorai/api/read.py
vectorai/api/search.py
vectorai/api/text.py
vectorai/api/utils.py
vectorai/api/write.py
vectorai/models/__init__.py
vectorai/models/base.py
vectorai/models/deployed/__init__.py
vectorai/models/deployed/audio.py
vectorai/models/deployed/base.py
vectorai/models/deployed/image.py
vectorai/models/deployed/text.py
vectorai-0.3.0.dist-info/LICENSE
vectorai-0.3.0.dist-info/METADATA
vectorai-0.3.0.dist-info/WHEEL
vectorai-0.3.0.dist-info/top_level.txt
vectorai-0.3.0.dist-info/RECORD
