Metadata-Version: 2.1
Name: vectorai
Version: 0.3.0
Summary: A Python framework for building vector based applications. Encode, query and analyse data using vectors.
Home-page: https://github.com/vector-ai/vectorai
Author: OnSearch Pty Ltd
Author-email: dev@vctr.ai
License: Apache
Keywords: vector,embeddings,machinelearning,ai,artificialintelligence,nlp,tensorflow,pytorch,nearestneighbors,search,analytics,clustering,dimensionalityreduction
Platform: UNKNOWN
Classifier: Development Status :: 5 - Production/Stable
Classifier: Intended Audience :: Developers
Classifier: Intended Audience :: Education
Classifier: Intended Audience :: Science/Research
Classifier: Intended Audience :: Information Technology
Classifier: Intended Audience :: Financial and Insurance Industry
Classifier: Intended Audience :: Healthcare Industry
Classifier: Intended Audience :: Manufacturing
Classifier: License :: OSI Approved :: Apache Software License
Classifier: Operating System :: OS Independent
Classifier: Programming Language :: Python
Classifier: Programming Language :: Python :: 3
Classifier: Programming Language :: Python :: 3.4
Classifier: Programming Language :: Python :: 3.5
Classifier: Programming Language :: Python :: 3.6
Classifier: Programming Language :: Python :: 3.7
Classifier: Programming Language :: Python :: Implementation :: PyPy
Classifier: Topic :: Database
Classifier: Topic :: Internet :: WWW/HTTP :: Indexing/Search
Classifier: Topic :: Multimedia :: Sound/Audio :: Conversion
Classifier: Topic :: Multimedia :: Video :: Conversion
Classifier: Topic :: Scientific/Engineering :: Artificial Intelligence
Classifier: Topic :: Scientific/Engineering :: Image Recognition
Classifier: Topic :: Scientific/Engineering :: Information Analysis
Classifier: Topic :: Scientific/Engineering :: Visualization
Classifier: Topic :: Software Development :: Libraries :: Application Frameworks
Requires-Python: >=3
Requires-Dist: requests
Requires-Dist: numpy
Requires-Dist: pandas
Requires-Dist: appdirs (>=1.4.4)
Requires-Dist: tqdm (>=4.27.0)
Requires-Dist: plotly (>=4.0.0)
Provides-Extra: all
Requires-Dist: twine ; extra == 'all'
Requires-Dist: black ; extra == 'all'
Requires-Dist: pytest ; extra == 'all'
Requires-Dist: pytest-cov ; extra == 'all'
Requires-Dist: vectorai ; extra == 'all'
Requires-Dist: openapi-to-sdk ; extra == 'all'
Requires-Dist: pytest-rerunfailures ; extra == 'all'
Requires-Dist: sphinx-rtd-theme (>=0.5.0) ; extra == 'all'
Requires-Dist: nbsphinx (>=0.7.1) ; extra == 'all'
Provides-Extra: dev
Requires-Dist: twine ; extra == 'dev'
Requires-Dist: black ; extra == 'dev'
Requires-Dist: pytest ; extra == 'dev'
Requires-Dist: pytest-cov ; extra == 'dev'
Requires-Dist: vectorai ; extra == 'dev'
Requires-Dist: openapi-to-sdk ; extra == 'dev'
Provides-Extra: docs
Requires-Dist: sphinx-rtd-theme (>=0.5.0) ; extra == 'docs'
Requires-Dist: nbsphinx (>=0.7.1) ; extra == 'docs'
Provides-Extra: test
Requires-Dist: pytest ; extra == 'test'
Requires-Dist: pytest-cov ; extra == 'test'
Requires-Dist: pytest-rerunfailures ; extra == 'test'
